code_stat/__init__.py
code_stat/cli.py
code_stat/definitions.py
code_stat/bin/__init__.py
code_stat/bin/data_reader.py
code_stat/bin/logger.py
code_stat/bin/statistics.py
code_stat/data/default_ext_list.yml
code_stat/data/default_languages.json
code_stat/tests/__init__.py
code_stat/tests/test_statistics.py
code_stat/tests/test_utils.py
code_stat/utils/__init__.py
code_stat/utils/conversion_utils.py
code_stat/utils/files_and_folders_utils.py
code_stat/utils/print_utils.py
codestatistics-0.1.dist-info/LICENSE.txt
codestatistics-0.1.dist-info/METADATA
codestatistics-0.1.dist-info/WHEEL
codestatistics-0.1.dist-info/entry_points.txt
codestatistics-0.1.dist-info/top_level.txt
codestatistics-0.1.dist-info/RECORD
