Metadata-Version: 2.1
Name: codestatistics
Version: 0.1
Summary: A command line tool to generate code statistics for a given directory.
Home-page: https://github.com/abhinavshaw1993/code-stat
Author: Abhinav Shaw
Author-email: abhinav.shaw1993@gmail.com
License: UNKNOWN
Platform: UNKNOWN
Classifier: Programming Language :: Python :: 3
Classifier: Operating System :: POSIX :: Linux
Requires-Dist: click
Requires-Dist: pathlib
